ecg_i2s/__init__.py
ecg_i2s/ecgnew.py
GFICLEE-1.0.dist-info/METADATA
GFICLEE-1.0.dist-info/WHEEL
GFICLEE-1.0.dist-info/entry_points.txt
GFICLEE-1.0.dist-info/top_level.txt
GFICLEE-1.0.dist-info/RECORD
